CHANGELOG.txt
LICENSE.txt
MANIFEST.in
README.txt
setup.py
physics/physik.py
physik.egg-info/PKG-INFO
physik.egg-info/SOURCES.txt
physik.egg-info/dependency_links.txt
physik.egg-info/top_level.txt