Metadata-Version: 1.1
Name: physik
Version: 0.0.1
Summary: A python physics library
Home-page: UNKNOWN
Author: Miguel Barroso
Author-email: miguelferreirabarroso6@gmail.com
License: MIT
Keywords: physics
Platform: UNKNOWN
Classifier: Development Status :: 5 - Production/Stable
Classifier: Intended Audience :: Education
Classifier: Operating System :: Microsoft :: Windows :: Windows 10
Classifier: License :: OSI Approved :: MIT License
Classifier: Programming Language :: Python :: 3
